piper_kit/__init__.py
piper_kit/interface.py
piper_kit/_cli/__init__.py
piper_kit/_cli/disable.py
piper_kit/_cli/enable.py
piper_kit/_cli/main.py
piper_kit/messages/__init__.py
piper_kit/messages/receive/__init__.py
piper_kit/messages/receive/joint_feedback.py
piper_kit/messages/receive/motor_info_b.py
piper_kit/messages/receive/receive.py
piper_kit/messages/receive/unknown.py
piper_kit/messages/transmit/__init__.py
piper_kit/messages/transmit/enable_joint.py
piper_kit/messages/transmit/joint_control.py
piper_kit/messages/transmit/motion_control_b.py
piper_kit/messages/transmit/transmit.py
piper_kit-0.1.0.dist-info/METADATA
piper_kit-0.1.0.dist-info/WHEEL
piper_kit-0.1.0.dist-info/entry_points.txt
piper_kit-0.1.0.dist-info/licenses/LICENSE
piper_kit-0.1.0.dist-info/RECORD
