Metadata-Version: 2.4
Name: piper-kit
Version: 0.1.0
Summary: SDK and CLI tools for AgileX PiPER robotic arm
Project-URL: repository, https://github.com/threeal/piper-kit.git
Project-URL: issues, https://github.com/threeal/piper-kit/issues
Author-email: Alfi Maulana <alfi.maulana.f@gmail.com>
License-Expression: MIT
License-File: LICENSE
Keywords: agilex,automation,can-bus,cli,piper,robotic-arm,robotics,sdk
Classifier: Development Status :: 3 - Alpha
Classifier: Intended Audience :: Developers
Classifier: Intended Audience :: Science/Research
Classifier: License :: OSI Approved :: MIT License
Classifier: Operating System :: POSIX :: Linux
Classifier: Programming Language :: Python :: 3 :: Only
Classifier: Programming Language :: Python :: 3.13
Classifier: Topic :: Scientific/Engineering :: Artificial Intelligence
Classifier: Topic :: Software Development :: Libraries :: Python Modules
Classifier: Topic :: System :: Hardware :: Hardware Drivers
Requires-Python: >=3.13
Requires-Dist: python-can>=4.5.0
